README.txt
setup.py
ctext/__init__.py
ctext/ctext.py
ctext.egg-info/PKG-INFO
ctext.egg-info/SOURCES.txt
ctext.egg-info/dependency_links.txt
ctext.egg-info/requires.txt
ctext.egg-info/top_level.txt