Metadata-Version: 1.1
Name: ctext
Version: 0.264
Summary: Chinese Text Project API wrapper
Home-page: http://ctext.org/tools/api
Author: Donald Sturgeon
Author-email: chinesetextproject@gmail.com
License: UNKNOWN
Keywords: Chinese,text,API,ctext
Platform: UNKNOWN
Classifier: Programming Language :: Python
Classifier: Programming Language :: Python :: 3
Classifier: Development Status :: 2 - Pre-Alpha
Classifier: Intended Audience :: Developers
Classifier: License :: OSI Approved :: MIT License
Classifier: Operating System :: OS Independent
Classifier: Topic :: Software Development :: Libraries :: Python Modules
Classifier: Topic :: Text Processing :: Linguistic
